Workbook

Sheet Summary
G8: Financial Performance and Ratio Analysis of Hindustan Unilever (FY 2020–FY 2025)
G15: This project analyzes the financial performance of Hindustan Unilever from FY-2020 to FY-2025 using key financial ratios and revenue trend analysis. The study evaluates important financial indicators such as Debt-to-Equity Ratio, Asset Turnover Ratio, Debt Ratio, Equity Ratio, and Revenue Growth to understand the company’s financial stability and operational efficiency. The financial data used for the analysis was collected from Screener.in and organized using Microsoft Excel to perform calculations, create tables, and analyze financial trends over the period.
G29: Data Source: Screener.in – Publicly available financial statements.

Sheet Financial Data
A1: F
F4: Financial Perfromance of Hindustan Unilever of FY 2020-FY 2025
F8: Year | G8: Total Revenue(In Cr) | H8: Total Assets(In Cr) | I8: Total Debt(In Cr) | J8: Total Equity(In Cr)
F9: 2020 | G9: 39783 | H9: 20153 | I9: =11924 -> 11924 | J9: 8229
F10: 2021 | G10: 47028 | H10: 68740 | I10: =21066 -> 21066 | J10: 47674
F11: 2022 | G11: 52446 | H11: 70506 | I11: =1043+20402 -> 21445 | J11: 49061
F12: 2023 | G12: 60580 | H12: 73077 | I12: =1219+21554 -> 22773 | J12: 50304
F13: 2024 | G13: 61896 | H13: 78489 | I13: =1484+25787 -> 27271 | J13: 51218
F14: 2025 | G14: 63121 | H14: 79863 | I14: =1648+28813 -> 30461 | J14: 49402
F33: Why there is a sudden Increase of approx 40,000 Cr in FY-2021 in Hindustan Unilever ?
F49: Reason:
F51: A significant increase in the total asset base of Hindustan Unilever was observed in FY-2021. Total assets increased from ₹20,153 crore in FY-2020 to ₹68,740 crore in FY-2021. This sharp increase was mainly due to the recognition of intangible assets, which rose from ₹511 crore to ₹45,262 crore. The increase reflects the capitalization of brand-related assets and restructuring activities within the company.
F57: Asset Composition:
F59: Year | G59: Total Assets(In Cr) | H59: Intangible Assets(In Cr) | I59: % of Intangible Assets
F60: 2020 | G60: 20153 | H60: 511 | I60: =H60/G60 -> 0.025356026
F61: 2021 | G61: 68740 | H61: 45262 | I61: =H61/G61 -> 0.65845214

Sheet Ratio Analysis
E7: Ratio Analysis:
E10: Debt-To-Equity:
E13: Year | F13: Debt | G13: Equity | H13: Debt/Equity Ratio
E14: FY-2020 | F14: 11924 | G14: 8229 | H14: ='Financial Data'!I9/'Financial Data'!J9 -> 1.4490218
E15: FY-2025 | F15: 30461 | G15: 49402 | H15: ='Financial Data'!I14/'Financial Data'!J14 -> 0.61659447
E17: Interpretation:
E18: In FY-2020, the Debt-to-Equity ratio of Hindustan Unilever was 1.44, indicating a relatively higher reliance on debt financing. Over the years, the ratio declined to 0.62 in FY-2025, reflecting a stronger equity base and improved financial stability. The decline in the ratio indicates that the company has reduced its relative dependence on debt and maintained a healthier capital structure. The improvement in the ratio was mainly driven by a significant increase in the company’s equity base after FY-2021, which strengthened the overall balance sheet.
E28: Asset Turnover Ratio:
E30: Year | F30: Total Assets | G30: Total Revenue | H30: Total Revenue/Total Assets Ratio
E32: FY-2020 | F32: ='Financial Data'!H9 -> 20153 | G32: ='Financial Data'!G9 -> 39783 | H32: =G32/F32 -> 1.9740485
E33: FY-2025 | F33: ='Financial Data'!H14 -> 79863 | G33: ='Financial Data'!G14 -> 63121 | H33: =G33/F33 -> 0.790366
E36: Interpretation:
E37: The Asset Turnover Ratio of Hindustan Unilever decreased from 1.97 in FY-2020 to 0.79 in FY-2025, indicating lower asset utilization efficiency. The decline is primarily due to a significant increase in the company’s asset base, particularly intangible assets, without a proportional increase in revenue.
E43: Debt Ratio:
E45: Year | F45: Total Assets | G45: Total Debt | H45: Total Debt/Total Assets Ratio
E47: FY-2020 | F47: ='Financial Data'!H9 -> 20153 | G47: ='Financial Data'!I9 -> 11924 | H47: =G47/F47 -> 0.5916737
E48: FY-2025 | F48: ='Financial Data'!H14 -> 79863 | G48: ='Financial Data'!I14 -> 30461 | H48: =G48/F48 -> 0.38141567
E51: Interpretation:
E52: The Debt Ratio of Hindustan Unilever indicates the proportion of the company’s assets financed through borrowings. A moderate debt ratio suggests that the company maintains a balanced capital structure without excessive reliance on debt. Over the years, although total debt increased, the company continued to maintain a stable asset base, indicating controlled financial risk and responsible leverage management.
E59: Equity Ratio:
E61: Year | F61: Total Assets | G61: Total Equity | H61: Total Equity/Total Assets Ratio
E63: FY-2020 | F63: ='Financial Data'!H9 -> 20153 | G63: ='Financial Data'!J9 -> 8229 | H63: =G63/F63 -> 0.4083263
E64: FY-2025 | F64: ='Financial Data'!H14 -> 79863 | G64: ='Financial Data'!J14 -> 49402 | H64: =G64/F64 -> 0.61858433
E67: Interpretation:
E68: The Equity Ratio of Hindustan Unilever reflects the proportion of assets financed through shareholders’ equity. A higher equity ratio indicates stronger financial stability and lower dependence on external borrowings. The company maintains a strong equity base, suggesting a stable financial structure and greater protection for creditors and investors.
E75: Revenue Growth Ratio:
E77: Year | F77: Revenue | G77: Growth
E78: 2020 | F78: ='Financial Data'!G9 -> 39783 | G78: -
E79: 2021 | F79: ='Financial Data'!G10 -> 47028 | G79: =(F79-F78)/F78 -> 0.18211296
E80: 2022 | F80: ='Financial Data'!G11 -> 52446 | G80: =(F80-F79)/F79 -> 0.11520796
E81: 2023 | F81: ='Financial Data'!G12 -> 60580 | G81: =(F81-F80)/F80 -> 0.15509286
E82: 2024 | F82: ='Financial Data'!G13 -> 61896 | G82: =(F82-F81)/F81 -> 0.021723341
E83: 2025 | F83: ='Financial Data'!G14 -> 63121 | G83: =(F83-F82)/F82 -> 0.019791263
E84: Overall growth from 2020 to 2025 | G84: =(F83-F78)/F78 -> 0.58663248
E86: Interpretation:
E87: The revenue of Hindustan Unilever increased steadily from FY-2020 to FY-2025, showing an overall growth of about 58.6%. This indicates strong business expansion, stable product demand, and effective market presence in the FMCG industry.
E108: Key Insights:
E110: 1. Revenue increased by 58.6% from FY-2020 to FY-2025, showing steady business growth. 2. Asset base increased significantly due to recognition of intangible assets in FY-2021. 3. Debt-to-Equity ratio improved from 1.44 to 0.62, indicating stronger financial stability. 4. Asset turnover declined as asset growth was higher than revenue growth.
